breadcrumbs/__init__.py
breadcrumbs/apps.py
breadcrumbs/context_processors.py
breadcrumbs/mixins.py
breadcrumbs/service.py
breadcrumbs/utils.py
breadcrumbs/templates/breadcrumbs/breadcrumbs.html
breadcrumbs/templatetags/__init__.py
breadcrumbs/templatetags/breadcrumbs.py
breadcrumbs/tests/__init__.py
easy_breadcrumbs-0.0.3.dist-info/LICENSE
easy_breadcrumbs-0.0.3.dist-info/METADATA
easy_breadcrumbs-0.0.3.dist-info/WHEEL
easy_breadcrumbs-0.0.3.dist-info/top_level.txt
easy_breadcrumbs-0.0.3.dist-info/RECORD
